[
  {
    "tier": "citymun",
    "region": "OAV",
    "province": "ASIA PACIFIC",
    "name": "NEGARA BRUNEI DARUSSALAM"
  },
  {
    "tier": "citymun",
    "region": "OAV",
    "province": "ASIA PACIFIC",
    "name": "KINGDOM OF THAILAND"
  },
  {
    "tier": "citymun",
    "region": "OAV",
    "province": "ASIA PACIFIC",
    "name": "PEOPLES REPUBLIC OF CHINA"
  },
  {
    "tier": "citymun",
    "region": "OAV",
    "province": "ASIA PACIFIC",
    "name": "TAIWAN, ROC"
  },
  {
    "tier": "citymun",
    "region": "OAV",
    "province": "ASIA PACIFIC",
    "name": "AUSTRALIA"
  },
  {
    "tier": "citymun",
    "region": "OAV",
    "province": "ASIA PACIFIC",
    "name": "MALAYSIA"
  },
  {
    "tier": "citymun",
    "region": "OAV",
    "province": "ASIA PACIFIC",
    "name": "REPUBLIC OF KOREA"
  },
  {
    "tier": "citymun",
    "region": "OAV",
    "province": "ASIA PACIFIC",
    "name": "REPUBLIC OF SINGAPORE"
  },
  {
    "tier": "citymun",
    "region": "OAV",
    "province": "ASIA PACIFIC",
    "name": "JAPAN"
  },
  {
    "tier": "citymun",
    "region": "OAV",
    "province": "ASIA PACIFIC",
    "name": "NEW ZEALAND"
  },
  {
    "tier": "citymun",
    "region": "OAV",
    "province": "AMERICAS",
    "name": "AGANA"
  },
  {
    "tier": "citymun",
    "region": "OAV",
    "province": "AMERICAS",
    "name": "CANADA"
  },
  {
    "tier": "citymun",
    "region": "OAV",
    "province": "AMERICAS",
    "name": "UNITED STATES OF AMERICA"
  },
  {
    "tier": "citymun",
    "region": "OAV",
    "province": "MIDDLE EAST AND AFRICAS",
    "name": "UNITED ARAB EMIRATES"
  },
  {
    "tier": "citymun",
    "region": "OAV",
    "province": "MIDDLE EAST AND AFRICAS",
    "name": "REPUBLIC OF LEBANON"
  },
  {
    "tier": "citymun",
    "region": "OAV",
    "province": "MIDDLE EAST AND AFRICAS",
    "name": "STATE OF QATAR"
  },
  {
    "tier": "citymun",
    "region": "OAV",
    "province": "MIDDLE EAST AND AFRICAS",
    "name": "STATE OF KUWAIT"
  },
  {
    "tier": "citymun",
    "region": "OAV",
    "province": "MIDDLE EAST AND AFRICAS",
    "name": "KINGDOM OF BAHRAIN"
  },
  {
    "tier": "citymun",
    "region": "OAV",
    "province": "MIDDLE EAST AND AFRICAS",
    "name": "SULTANATE OF OMAN"
  },
  {
    "tier": "citymun",
    "region": "OAV",
    "province": "MIDDLE EAST AND AFRICAS",
    "name": "KINGDOM OF SAUDI ARABIA"
  },
  {
    "tier": "citymun",
    "region": "OAV",
    "province": "MIDDLE EAST AND AFRICAS",
    "name": "ISRAEL"
  },
  {
    "tier": "citymun",
    "region": "OAV",
    "province": "EUROPE",
    "name": "ATHENS"
  },
  {
    "tier": "citymun",
    "region": "OAV",
    "province": "EUROPE",
    "name": "UNITED KINGDOM OF GREAT BRITAIN"
  },
  {
    "tier": "citymun",
    "region": "OAV",
    "province": "EUROPE",
    "name": "KINGDOM OF SPAIN"
  },
  {
    "tier": "citymun",
    "region": "OAV",
    "province": "EUROPE",
    "name": "ITALY"
  }
]